linear_solvers/__init__.py
linear_solvers/hhl.py
linear_solvers/linear_solver.py
linear_solvers/numpy_linear_solver.py
linear_solvers/__pycache__/__init__.cpython-38.pyc
linear_solvers/__pycache__/__init__.cpython-39.pyc
linear_solvers/__pycache__/hhl.cpython-38.pyc
linear_solvers/__pycache__/hhl.cpython-39.pyc
linear_solvers/__pycache__/linear_solver.cpython-38.pyc
linear_solvers/__pycache__/linear_solver.cpython-39.pyc
linear_solvers/__pycache__/numpy_linear_solver.cpython-38.pyc
linear_solvers/__pycache__/numpy_linear_solver.cpython-39.pyc
linear_solvers/matrices/__init__.py
linear_solvers/matrices/linear_system_matrix.py
linear_solvers/matrices/numpy_matrix.py
linear_solvers/matrices/tridiagonal_toeplitz.py
linear_solvers/matrices/__pycache__/__init__.cpython-38.pyc
linear_solvers/matrices/__pycache__/__init__.cpython-39.pyc
linear_solvers/matrices/__pycache__/linear_system_matrix.cpython-38.pyc
linear_solvers/matrices/__pycache__/linear_system_matrix.cpython-39.pyc
linear_solvers/matrices/__pycache__/numpy_matrix.cpython-38.pyc
linear_solvers/matrices/__pycache__/numpy_matrix.cpython-39.pyc
linear_solvers/matrices/__pycache__/tridiagonal_toeplitz.cpython-38.pyc
linear_solvers/matrices/__pycache__/tridiagonal_toeplitz.cpython-39.pyc
linear_solvers/observables/__init__.py
linear_solvers/observables/absolute_average.py
linear_solvers/observables/linear_system_observable.py
linear_solvers/observables/matrix_functional.py
linear_solvers/observables/__pycache__/__init__.cpython-38.pyc
linear_solvers/observables/__pycache__/__init__.cpython-39.pyc
linear_solvers/observables/__pycache__/absolute_average.cpython-38.pyc
linear_solvers/observables/__pycache__/absolute_average.cpython-39.pyc
linear_solvers/observables/__pycache__/linear_system_observable.cpython-38.pyc
linear_solvers/observables/__pycache__/linear_system_observable.cpython-39.pyc
linear_solvers/observables/__pycache__/matrix_functional.cpython-38.pyc
quantum_linear_solvers-0.1.1.dist-info/LICENSE
quantum_linear_solvers-0.1.1.dist-info/METADATA
quantum_linear_solvers-0.1.1.dist-info/WHEEL
quantum_linear_solvers-0.1.1.dist-info/top_level.txt
quantum_linear_solvers-0.1.1.dist-info/RECORD
