Metadata-Version: 2.1
Name: quantum-linear-solvers
Version: 0.1.1
Summary: Quantum linear solvers package for qiskit
License: Apache License 2.0
Classifier: License :: OSI Approved :: Apache Software License
Classifier: Programming Language :: Python :: 3
Classifier: Programming Language :: Python :: 3.7
Classifier: Programming Language :: Python :: 3.8
Classifier: Programming Language :: Python :: 3.9
Classifier: Programming Language :: Python :: 3.10
Classifier: Programming Language :: Python :: 3.11
Classifier: Topic :: Scientific/Engineering :: Physics
Requires-Python: >=3.7, <4
License-File: LICENSE
Requires-Dist: importlib-metadata
Requires-Dist: mapomatic ==0.6
Requires-Dist: mthree ==0.24
Requires-Dist: pylatexenc
Requires-Dist: qiskit-aer
Requires-Dist: qiskit-ibmq-provider
Requires-Dist: qiskit-terra >=0.21
